{
  "meta": {
    "stableOrder": true
  },
  "lockfileVersion": 3,
  "ATTENTION": "THIS IS AN AUTOGENERATED FILE. DO NOT EDIT THIS FILE DIRECTLY.",
  "specifiers": {
    "@abner/log@^1.0.3": "@abner/log@1.0.3",
    "@blend/base@base": "@blend/base@base",
    "@blend/basic@basic": "@blend/basic@basic",
    "@blend/buttonLibrary@buttonLibrary": "@blend/buttonLibrary@buttonLibrary",
    "@blend/interview@interview": "@blend/interview@interview",
    "@blend/wechat@wechat": "@blend/wechat@wechat",
    "@blend/xsd@xsd": "@blend/xsd@xsd",
    "@care/basic@care/common/care_basic": "@care/basic@care/common/care_basic",
    "@guardian/guardian@guardian/guardian": "@guardian/guardian@guardian/guardian",
    "@guardian/test@guardian/test": "@guardian/test@guardian/test",
    "@hview/dayjs@^1.11.11": "@hview/dayjs@1.11.11",
    "@itheima/wing-care@^1.0.2": "@itheima/wing-care@1.0.2",
    "@ohmos/calendar@^2.1.3": "@ohmos/calendar@2.1.4",
    "@ohmos/sku@^1.0.1": "@ohmos/sku@1.0.1",
    "@ohos/axios@^2.2.0": "@ohos/axios@2.2.4",
    "@ohos/axios@^2.2.3": "@ohos/axios@2.2.4",
    "@ohos/axios@^2.2.4": "@ohos/axios@2.2.4",
    "@ohos/crypto-js@2.0.4-rc.1": "@ohos/crypto-js@2.0.4-rc.1",
    "@ohos/hypium@1.0.6": "@ohos/hypium@1.0.6",
    "@ohos/lottie@^2.0.9": "@ohos/lottie@2.0.14",
    "@shop/basic@shop/common/shop_basic": "@shop/basic@shop/common/shop_basic",
    "@shop/cart@shop/features/shop_cart": "@shop/cart@shop/features/shop_cart",
    "@shop/category@shop/features/shop_category": "@shop/category@shop/features/shop_category",
    "@shop/home@shop/features/shop_home": "@shop/home@shop/features/shop_home",
    "@shop/index@shop/index/shop_index": "@shop/index@shop/index/shop_index",
    "@shop/mine@shop/features/shop_mine": "@shop/mine@shop/features/shop_mine",
    "@wolfx/lodash@^4.17.21-rc.2": "@wolfx/lodash@4.17.21-rc.2",
    "dayjs@1.11.7": "dayjs@1.11.13",
    "dayjs@^1.11.7": "dayjs@1.11.13"
  },
  "packages": {
    "@abner/log@1.0.3": {
      "name": "@abner/log",
      "version": "1.0.3",
      "integrity": "sha512-NUlTvqJtUDlih1ovpSCQ5YkY6eXbEn94hfm4TUiV92FSVRqhrQTvSYfmiMRtKjHjHKQedAqWL2iVnJ9syGwaaw==",
      "resolved": "https://ohpm.openharmony.cn/ohpm/@abner/log/-/log-1.0.3.har",
      "registryType": "ohpm"
    },
    "@blend/base@base": {
      "name": "base",
      "version": "1.0.0",
      "resolved": "base",
      "registryType": "local",
      "dependencies": {
        "@ohos/axios": "^2.2.0"
      }
    },
    "@blend/basic@basic": {
      "name": "basic",
      "version": "1.0.0",
      "resolved": "basic",
      "registryType": "local"
    },
    "@blend/buttonLibrary@buttonLibrary": {
      "name": "buttonlibrary",
      "version": "1.0.0",
      "resolved": "buttonLibrary",
      "registryType": "local"
    },
    "@blend/interview@interview": {
      "name": "interview",
      "version": "1.0.0",
      "resolved": "interview",
      "registryType": "local",
      "dependencies": {
        "@ohos/axios": "^2.2.3",
        "@ohmos/calendar": "^2.1.3",
        "@hview/dayjs": "^1.11.11"
      },
      "packageType": "InterfaceHar"
    },
    "@blend/wechat@wechat": {
      "name": "wechat",
      "version": "1.0.0",
      "resolved": "wechat",
      "registryType": "local",
      "packageType": "InterfaceHar"
    },
    "@blend/xsd@xsd": {
      "name": "xsd",
      "version": "1.0.0",
      "resolved": "xsd",
      "registryType": "local",
      "dependencies": {
        "@blend/basic": "file:../basic"
      },
      "packageType": "InterfaceHar"
    },
    "@care/basic@care/common/care_basic": {
      "name": "care_basic",
      "version": "1.0.0",
      "resolved": "care/common/care_basic",
      "registryType": "local",
      "packageType": "InterfaceHar"
    },
    "@guardian/guardian@guardian/guardian": {
      "name": "guardian",
      "version": "1.0.0",
      "resolved": "guardian/guardian",
      "registryType": "local",
      "dependencies": {
        "@ohos/crypto-js": "2.0.4-rc.1",
        "@wolfx/lodash": "^4.17.21-rc.2"
      },
      "packageType": "InterfaceHar"
    },
    "@guardian/test@guardian/test": {
      "name": "test",
      "version": "1.0.0",
      "resolved": "guardian/test",
      "registryType": "local",
      "packageType": "InterfaceHar"
    },
    "@hview/dayjs@1.11.11": {
      "name": "@hview/dayjs",
      "version": "1.11.11",
      "integrity": "sha512-JPJlAbcCS8STHIRnesbAPWCF6eAlIkGx5rDPGT8CesSCMsB6ZJWEH+l3hl0YqtmfofCCVpWrzjBG7Z2f18olAw==",
      "resolved": "https://ohpm.openharmony.cn/ohpm/@hview/dayjs/-/dayjs-1.11.11.har",
      "registryType": "ohpm"
    },
    "@itheima/wing-care@1.0.2": {
      "name": "@itheima/wing-care",
      "version": "1.0.2",
      "integrity": "sha512-uCO7/a2ci1h/kVDFZJob4t62XGf4uj/L5LR279GxoTRZwEpFTcULika+m6+NCTe5NTtKAW/wLdh2Dm2MCfjuPA==",
      "resolved": "https://ohpm.openharmony.cn/ohpm/@itheima/wing-care/-/wing-care-1.0.2.har",
      "registryType": "ohpm"
    },
    "@ohmos/calendar@2.1.4": {
      "name": "@ohmos/calendar",
      "version": "2.1.4",
      "integrity": "sha512-gKDycOjzRQUQl66VoZznuoyKnZta1ySICDdW9EaGPL85f3FHmGYQJrpc1eWx2wZdcuW/k08ryAGuXW/GDJEQ2w==",
      "resolved": "https://ohpm.openharmony.cn/ohpm/@ohmos/calendar/-/calendar-2.1.4.har",
      "registryType": "ohpm",
      "dependencies": {
        "dayjs": "1.11.7"
      }
    },
    "@ohmos/sku@1.0.1": {
      "name": "@ohmos/sku",
      "version": "1.0.1",
      "integrity": "sha512-LreAMlMUc0VEqBEjq2+U/A1y1aMe6rwTzi4yboYc8Y5uJFZvO/P9p/uOzpGoJF6h+XQmGmTsDmlEAJXc/bGW/A==",
      "resolved": "https://ohpm.openharmony.cn/ohpm/@ohmos/sku/-/sku-1.0.1.har",
      "registryType": "ohpm"
    },
    "@ohos/axios@2.2.4": {
      "name": "@ohos/axios",
      "version": "2.2.4",
      "integrity": "sha512-5oH753kGFwfJP1kvCnI92RRaSqRbN0b24vmNNrUV+T8+5ako98rtVQOhA7ezMPox5Z3PFWndLQTF/P/hEK/yeQ==",
      "resolved": "https://repo.harmonyos.com/ohpm/@ohos/axios/-/axios-2.2.4.har",
      "registryType": "ohpm"
    },
    "@ohos/crypto-js@2.0.4-rc.1": {
      "name": "@ohos/crypto-js",
      "version": "2.0.4-rc.1",
      "integrity": "sha512-RZ/9BugTAS/DcMwYfcSvsCWRKf6hqZNgm6+gpqTqFs4P3dk2agUqiMEx5JHBAKUh6YMi0MXMCPf8NtHeT1CabA==",
      "resolved": "https://ohpm.openharmony.cn/ohpm/@ohos/crypto-js/-/crypto-js-2.0.4-rc.1.har",
      "registryType": "ohpm"
    },
    "@ohos/hypium@1.0.6": {
      "name": "@ohos/hypium",
      "version": "1.0.6",
      "integrity": "sha512-bb3DWeWhYrFqj9mPFV3yZQpkm36kbcK+YYaeY9g292QKSjOdmhEIQR2ULPvyMsgSR4usOBf5nnYrDmaCCXirgQ==",
      "resolved": "https://ohpm.openharmony.cn/ohpm/@ohos/hypium/-/hypium-1.0.6.tgz",
      "shasum": "3f5fed65372633233264b3447705b0831dfe7ea1",
      "registryType": "ohpm"
    },
    "@ohos/lottie@2.0.14": {
      "name": "@ohos/lottie",
      "version": "2.0.14",
      "integrity": "sha512-9CGDIbXuU0Sy1KjG84KCa4avpUdYXISISH8czosHa40apdf+hFGNYeH9QLFw/KoO+/JNYtTc6E7xuNB2iZuhRg==",
      "resolved": "https://ohpm.openharmony.cn/ohpm/@ohos/lottie/-/lottie-2.0.14.har",
      "registryType": "ohpm"
    },
    "@shop/basic@shop/common/shop_basic": {
      "name": "shop_basic",
      "version": "1.0.0",
      "resolved": "shop/common/shop_basic",
      "registryType": "local",
      "dependencies": {
        "@abner/log": "^1.0.3",
        "@ohos/axios": "^2.2.4",
        "@ohmos/sku": "^1.0.1"
      },
      "packageType": "InterfaceHar"
    },
    "@shop/cart@shop/features/shop_cart": {
      "name": "shop_cart",
      "version": "1.0.0",
      "resolved": "shop/features/shop_cart",
      "registryType": "local",
      "dependencies": {
        "@shop/basic": "file:../../common/shop_basic"
      },
      "packageType": "InterfaceHar"
    },
    "@shop/category@shop/features/shop_category": {
      "name": "shop_category",
      "version": "1.0.0",
      "resolved": "shop/features/shop_category",
      "registryType": "local",
      "dependencies": {
        "@shop/basic": "file:../../common/shop_basic"
      },
      "packageType": "InterfaceHar"
    },
    "@shop/home@shop/features/shop_home": {
      "name": "shop_home",
      "version": "1.0.0",
      "resolved": "shop/features/shop_home",
      "registryType": "local",
      "dependencies": {
        "@shop/basic": "file:../../common/shop_basic"
      },
      "packageType": "InterfaceHar"
    },
    "@shop/index@shop/index/shop_index": {
      "name": "shop_index",
      "version": "1.0.0",
      "resolved": "shop/index/shop_index",
      "registryType": "local",
      "dependencies": {
        "@shop/basic": "file:../../common/shop_basic",
        "@shop/home": "file:../../features/shop_home",
        "@shop/mine": "file:../../features/shop_mine",
        "@shop/category": "file:../../features/shop_category",
        "@shop/cart": "file:../../features/shop_cart"
      },
      "packageType": "InterfaceHar"
    },
    "@shop/mine@shop/features/shop_mine": {
      "name": "shop_mine",
      "version": "1.0.0",
      "resolved": "shop/features/shop_mine",
      "registryType": "local",
      "dependencies": {
        "@shop/basic": "file:../../common/shop_basic"
      },
      "packageType": "InterfaceHar"
    },
    "@wolfx/lodash@4.17.21-rc.2": {
      "name": "@wolfx/lodash",
      "version": "4.17.21-rc.2",
      "integrity": "sha512-W4YKGPkW3UTTfmzNJ0kBYe7Vb/s3fVg0RV23W6Acnz7i6QX0t/ztV1JJbKb/bPP0e1htyRHvDrrIYZVtI/HA2w==",
      "resolved": "https://ohpm.openharmony.cn/ohpm/@wolfx/lodash/-/lodash-4.17.21-rc.2.har",
      "registryType": "ohpm"
    },
    "dayjs@1.11.13": {
      "name": "dayjs",
      "version": "1.11.13",
      "integrity": "sha512-oaMBel6gjolK862uaPQOVTA7q3TZhuSvuMQAAglQDOWYO9A91IrAOUJEyKVlqJlHE0vq5p5UXxzdPfMH/x6xNg==",
      "resolved": "https://ohpm.openharmony.cn/ohpm/dayjs/-/dayjs-1.11.13.tgz",
      "shasum": "92430b0139055c3ebb60150aa13e860a4b5a366c",
      "registryType": "ohpm"
    }
  }
}